PhyPraKit/__init__.py
PhyPraKit/_version_info.py
PhyPraKit/csv2yml.py
PhyPraKit/phyFit.py
PhyPraKit/phyTools.py
PhyPraKit/plotCSV.py
PhyPraKit/plotData.py
PhyPraKit/run_phyFit.py
PhyPraKit/smoothCSV.py
PhyPraKit-1.2.10.data/scripts/csv2yml.py
PhyPraKit-1.2.10.data/scripts/plotCSV.py
PhyPraKit-1.2.10.data/scripts/plotData.py
PhyPraKit-1.2.10.data/scripts/run_phyFit.py
PhyPraKit-1.2.10.data/scripts/smoothCSV.py
PhyPraKit-1.2.10.dist-info/AUTHORS
PhyPraKit-1.2.10.dist-info/LICENSE
PhyPraKit-1.2.10.dist-info/METADATA
PhyPraKit-1.2.10.dist-info/WHEEL
PhyPraKit-1.2.10.dist-info/top_level.txt
PhyPraKit-1.2.10.dist-info/RECORD
