Metadata-Version: 2.1
Name: PhyPraKit
Version: 1.2.10
Summary: Tools for data visualisation and analysis in Physics Lab Courses
Home-page: http://www.etp.kit.edu/~quast/
Author: Guenter Quast
Author-email: Guenter.Quast@online.de
License: GNU Public Licence
Classifier: Development Status :: 5 - Production/Stable
Classifier: Programming Language :: Python :: 2.7
Classifier: Programming Language :: Python :: 3.6
Classifier: Programming Language :: Python :: 3.7
Classifier: Programming Language :: Python :: 3.8
Classifier: Programming Language :: Python :: 3.9
Classifier: Programming Language :: Python :: 3.10
Classifier: Programming Language :: Python :: 3.11
Classifier: Programming Language :: Python :: 3.12
License-File: LICENSE
License-File: AUTHORS
Requires-Dist: NumPy
Requires-Dist: SciPy
Requires-Dist: argparse
Requires-Dist: matplotlib
Requires-Dist: npy-append-array
Requires-Dist: pathlib
Requires-Dist: scikit-learn
